efficient_det/__init__.py
efficient_det/hyper_parameter_search.py
efficient_det/losses.py
efficient_det/run_hyper_parameter_search.py
efficient_det/run_training.py
efficient_det/train.py
efficient_det/callbacks/__init__.py
efficient_det/callbacks/eval.py
efficient_det/configuration/__init__.py
efficient_det/configuration/constants.py
efficient_det/configuration/model_params.py
efficient_det/layers/__init__.py
efficient_det/layers/activation_layer.py
efficient_det/layers/filter_predictions.py
efficient_det/models/__init__.py
efficient_det/models/efficient_det.py
efficient_det/models/efficient_net.py
efficient_det/models/feature_pyramid_network.py
efficient_det/preprocessing/__init__.py
efficient_det/preprocessing/generator.py
efficient_det/utils/__init__.py
efficient_det/utils/anchors.py
efficient_det/utils/config_parser.py
efficient_det/utils/eval.py
efficient_det/utils/image.py
efficient_det/utils/logs.py
efficient_det/utils/overlap.py
efficient_det/utils/parser.py
efficient_det/utils/scale_model.py
efficient_det/utils/targets.py
efficient_det/utils/visualization.py
efficient_det-0.1.3.dist-info/LICENSE
efficient_det-0.1.3.dist-info/METADATA
efficient_det-0.1.3.dist-info/WHEEL
efficient_det-0.1.3.dist-info/top_level.txt
efficient_det-0.1.3.dist-info/RECORD
