Metadata-Version: 2.1
Name: efficient-det
Version: 0.1.3
Summary: Efficient-Det Implementation in Keras
Home-page: https://git.hhu.de/zeboz100/efficientdet
Author: Zeynep Boztoprak
Author-email: zeynep.boztoprak@hhu.de
License: UNKNOWN
Project-URL: Bug Tracker, https://git.hhu.de/zeboz100/efficientdet/-/issues
Platform: UNKNOWN
Classifier: Programming Language :: Python :: 3
Classifier: License :: OSI Approved :: Apache Software License
Classifier: Operating System :: OS Independent
Requires-Python: >=3.6, !=3.9.*
License-File: LICENSE
Requires-Dist: tabulate
Requires-Dist: ray[default] (>=1.3.0)
Requires-Dist: ray[tune]
Requires-Dist: matplotlib
Requires-Dist: wandb
Requires-Dist: pillow
Requires-Dist: progressbar2
Requires-Dist: pandas
Requires-Dist: opencv-python
Provides-Extra: cpu
Requires-Dist: tensorflow (>=2.3.0) ; extra == 'cpu'
Provides-Extra: gpu
Requires-Dist: tensorflow-gpu (>=2.3.0) ; extra == 'gpu'
